stocktrends/__init__.py
stocktrends/indicators.py
stocktrends-0.1.6.dist-info/licenses/LICENSE.txt
tests/__init__.py
tests/test_indicators.py
stocktrends-0.1.6.dist-info/METADATA
stocktrends-0.1.6.dist-info/WHEEL
stocktrends-0.1.6.dist-info/top_level.txt
stocktrends-0.1.6.dist-info/RECORD
